dvclive/__init__.py
dvclive/_dvclive_version.py
dvclive/dvc.py
dvclive/env.py
dvclive/error.py
dvclive/fabric.py
dvclive/fastai.py
dvclive/huggingface.py
dvclive/keras.py
dvclive/lgbm.py
dvclive/lightning.py
dvclive/live.py
dvclive/monitor_system.py
dvclive/optuna.py
dvclive/py.typed
dvclive/report.py
dvclive/serialize.py
dvclive/studio.py
dvclive/utils.py
dvclive/vscode.py
dvclive/xgb.py
dvclive/plots/__init__.py
dvclive/plots/base.py
dvclive/plots/custom.py
dvclive/plots/image.py
dvclive/plots/metric.py
dvclive/plots/sklearn.py
dvclive/plots/utils.py
dvclive-3.48.4.dist-info/licenses/LICENSE
dvclive-3.48.4.dist-info/METADATA
dvclive-3.48.4.dist-info/WHEEL
dvclive-3.48.4.dist-info/top_level.txt
dvclive-3.48.4.dist-info/RECORD
