Metadata-Version: 2.4
Name: dvclive
Version: 3.48.4
Summary: Experiments logger for ML projects.
Author-email: Iterative <support@dvc.org>
Maintainer-email: Iterative <support@dvc.org>
License-Expression: Apache-2.0
Project-URL: Homepage, https://github.com/iterative/dvclive
Project-URL: Documentation, https://dvc.org/doc/dvclive
Project-URL: Repository, https://github.com/iterative/dvclive
Project-URL: Changelog, https://github.com/iterative/dvclive/releases
Project-URL: Issues, https://github.com/iterative/dvclive/issues
Keywords: ai,metrics,collaboration,data-science,data-version-control,developer-tools,git,machine-learning,reproducibility
Classifier: Development Status :: 4 - Beta
Classifier: Programming Language :: Python :: 3
Classifier: Programming Language :: Python :: 3.9
Classifier: Programming Language :: Python :: 3.10
Classifier: Programming Language :: Python :: 3.11
Classifier: Programming Language :: Python :: 3.12
Requires-Python: >=3.9
License-File: LICENSE
Requires-Dist: dvc>=3.48.4
Requires-Dist: dvc-render<2,>=1.0.0
Requires-Dist: dvc-studio-client<1,>=0.20
Requires-Dist: funcy
Requires-Dist: gto
Requires-Dist: ruamel.yaml
Requires-Dist: scmrepo<4,>=3
Requires-Dist: psutil
Requires-Dist: pynvml
Provides-Extra: image
Requires-Dist: numpy; extra == "image"
Requires-Dist: pillow; extra == "image"
Provides-Extra: sklearn
Requires-Dist: scikit-learn>=1.5.0; extra == "sklearn"
Provides-Extra: plots
Requires-Dist: scikit-learn; extra == "plots"
Requires-Dist: pandas; extra == "plots"
Requires-Dist: numpy; extra == "plots"
Provides-Extra: markdown
Requires-Dist: matplotlib; extra == "markdown"
Provides-Extra: tests
Requires-Dist: pytest<9.0,>=7.2.0; extra == "tests"
Requires-Dist: pytest-sugar<2.0,>=0.9.6; extra == "tests"
Requires-Dist: pytest-cov<7.0,>=3.0.0; extra == "tests"
Requires-Dist: pytest-mock<4.0,>=3.8.2; extra == "tests"
Requires-Dist: dvclive[image,markdown,plots]; extra == "tests"
Requires-Dist: ipython; extra == "tests"
Requires-Dist: pytest_voluptuous; extra == "tests"
Requires-Dist: dpath; extra == "tests"
Requires-Dist: transformers[torch]; extra == "tests"
Requires-Dist: tf-keras; extra == "tests"
Provides-Extra: dev
Requires-Dist: dvclive[all,tests]; extra == "dev"
Requires-Dist: mypy==1.17.1; extra == "dev"
Requires-Dist: types-PyYAML; extra == "dev"
Provides-Extra: mmcv
Requires-Dist: mmcv; extra == "mmcv"
Provides-Extra: tf
Requires-Dist: tensorflow; extra == "tf"
Provides-Extra: xgb
Requires-Dist: xgboost; extra == "xgb"
Provides-Extra: lgbm
Requires-Dist: lightgbm; extra == "lgbm"
Provides-Extra: huggingface
Requires-Dist: transformers; extra == "huggingface"
Requires-Dist: datasets; extra == "huggingface"
Provides-Extra: fastai
Requires-Dist: fastai; extra == "fastai"
Provides-Extra: lightning
Requires-Dist: lightning>=2.0; extra == "lightning"
Requires-Dist: torch; extra == "lightning"
Requires-Dist: jsonargparse[signatures]>=4.26.1; extra == "lightning"
Provides-Extra: optuna
Requires-Dist: optuna; extra == "optuna"
Provides-Extra: all
Requires-Dist: dvclive[fastai,huggingface,image,lgbm,lightning,markdown,mmcv,optuna,plots,tf,xgb]; extra == "all"
Dynamic: license-file
